hapnet/__init__.py
hapnet/cli.py
hapnet/distance.py
hapnet/haplotypes.py
hapnet/io.py
hapnet/logs.py
hapnet/network.py
hapnet/plot.py
hapnet/summary.py
hapnet-0.1.0.dist-info/licenses/LICENSE
hapnet-0.1.0.dist-info/METADATA
hapnet-0.1.0.dist-info/WHEEL
hapnet-0.1.0.dist-info/entry_points.txt
hapnet-0.1.0.dist-info/top_level.txt
hapnet-0.1.0.dist-info/RECORD
