Metadata-Version: 2.4
Name: hapnet
Version: 0.1.0
Summary: Population-aware haplotype network analysis and visualization in Python.
Author: Andrew A. Davinack
License: MIT
Project-URL: Homepage, https://github.com/parasiteguy/hapnet
Project-URL: Repository, https://github.com/parasiteguy/hapnet
Project-URL: Issues, https://github.com/parasiteguy/hapnet/issues
Classifier: Development Status :: 3 - Alpha
Classifier: Intended Audience :: Science/Research
Classifier: License :: OSI Approved :: MIT License
Classifier: Programming Language :: Python :: 3
Classifier: Programming Language :: Python :: 3.9
Classifier: Programming Language :: Python :: 3.10
Classifier: Programming Language :: Python :: 3.11
Classifier: Programming Language :: Python :: 3.12
Classifier: Topic :: Scientific/Engineering :: Bio-Informatics
Requires-Python: >=3.9
License-File: LICENSE
Requires-Dist: biopython>=1.80
Requires-Dist: networkx>=3.0
Requires-Dist: matplotlib>=3.7
Requires-Dist: numpy>=1.24
Requires-Dist: scipy>=1.9
Dynamic: license-file
